globalpayments/__init__.py
globalpayments/api/__init__.py
globalpayments/api/builders/__init__.py
globalpayments/api/builders/request_builder/GpApi/AccessTokenRequest.py
globalpayments/api/builders/request_builder/GpApi/GpApiAuthorizationRequestBuilder.py
globalpayments/api/builders/request_builder/GpApi/GpApiManagementRequestBuilder.py
globalpayments/api/builders/request_builder/GpApi/GpApiMiCRequestBuilder.py
globalpayments/api/builders/request_builder/GpApi/GpApiReportRequestBuilder.py
globalpayments/api/builders/request_builder/GpApi/GpApiSecureRequestBuilder.py
globalpayments/api/builders/request_builder/GpApi/GpApiSessionInfo.py
globalpayments/api/builders/request_builder/GpApi/__init__.py
globalpayments/api/builders/request_builder/GpEcom/GpEcomAuthorizationRequestBuilder.py
globalpayments/api/builders/request_builder/GpEcom/GpEcomManagementRequestBuilder.py
globalpayments/api/builders/request_builder/GpEcom/GpEcomRequestBuilder.py
globalpayments/api/builders/request_builder/GpEcom/__init__.py
globalpayments/api/builders/request_builder/IRequestBuilder.py
globalpayments/api/builders/request_builder/RequestBuilderFactory.py
globalpayments/api/builders/request_builder/__init__.py
globalpayments/api/builders/secure_builder.py
globalpayments/api/builders/threeD_secure_builder.py
globalpayments/api/builders/validations/__init__.py
globalpayments/api/builders/validations/validation_clause.py
globalpayments/api/builders/validations/validation_target.py
globalpayments/api/builders/validations/validations.py
globalpayments/api/entities/__init__.py
globalpayments/api/entities/address.py
globalpayments/api/entities/address.py.bak
globalpayments/api/entities/alternative_payment_response.py
globalpayments/api/entities/batch_summary.py
globalpayments/api/entities/browser_data.py
globalpayments/api/entities/card.py
globalpayments/api/entities/card_issuer_response.py
globalpayments/api/entities/dcc_rate_data.py
globalpayments/api/entities/debit_mac.py
globalpayments_api-2.0.6.dist-info/LICENSE.md
globalpayments_api-2.0.6.dist-info/METADATA
globalpayments_api-2.0.6.dist-info/WHEEL
globalpayments_api-2.0.6.dist-info/entry_points.txt
globalpayments_api-2.0.6.dist-info/RECORD
