Metadata-Version: 2.3
Name: GlobalPayments.Api
Version: 2.0.6
Summary: Global Payments Python SDK for integrating with Global Payments merchant services APIs
License: LICENSE.md
Author: Global Payments
Author-email: EntApp_DevPortal@e-hps.com
Requires-Python: >=3.11,<4.0
Classifier: License :: Other/Proprietary License
Classifier: Programming Language :: Python :: 3
Classifier: Programming Language :: Python :: 3.11
Classifier: Programming Language :: Python :: 3.12
Classifier: Programming Language :: Python :: 3.13
Requires-Dist: certifi (>=2024.12.14,<2025.0.0)
Requires-Dist: dateparser (>=1.2.1,<2.0.0)
Requires-Dist: enum34 (>=1.1.10,<2.0.0)
Requires-Dist: idna (>=3.10,<4.0)
Requires-Dist: jsonpickle (>=4.0.1,<5.0.0)
Requires-Dist: pyopenssl (>=24.3.0,<25.0.0)
Requires-Dist: requests (>=2.32.3,<3.0.0)
Requires-Dist: urllib3 (>=2.3.0,<3.0.0)
Requires-Dist: xmltodict (>=0.14.2,<0.15.0)
Project-URL: Homepage, https://developer.globalpay.com/
